<?xml version="1.0"?>
<CZPTTCISMessage xmlns:xsd="http://www.w3.org/2001/XMLSchema" xmlns:xsi="http://www.w3.org/2001/XMLSchema-instance">
  <Identifiers>
    <PlannedTransportIdentifiers>
      <ObjectType>PA</ObjectType>
      <Company>0054</Company>
      <Core>KT----67296A</Core>
      <Variant>00</Variant>
      <TimetableYear>2026</TimetableYear>
    </PlannedTransportIdentifiers>
    <PlannedTransportIdentifiers>
      <ObjectType>TR</ObjectType>
      <Company>3736</Company>
      <Core>-LB125033962</Core>
      <Variant>00</Variant>
      <TimetableYear>2026</TimetableYear>
    </PlannedTransportIdentifiers>
  </Identifiers>
  <CZPTTCreation>2025-11-05T15:39:30</CZPTTCreation>
  <CZPTTHeader />
  <CZPTTInformation>
    <CZPTTLocation>
      <Location>
        <CountryCodeISO>CZ</CountryCodeISO>
        <LocationPrimaryCode>76094</LocationPrimaryCode>
        <PrimaryLocationName>Rakovník</PrimaryLocationName>
        <LocationSubsidiaryIdentification>
          <LocationSubsidiaryCode LocationSubsidiaryTypeCode="1">1</LocationSubsidiaryCode>
          <AllocationCompany>0054</AllocationCompany>
        </LocationSubsidiaryIdentification>
      </Location>
      <TimingAtLocation>
        <Timing TimingQualifierCode="ALD">
          <Time>11:50:00.0000000+01:00</Time>
          <Offset>0</Offset>
        </Timing>
      </TimingAtLocation>
      <ResponsibleRU>3736</ResponsibleRU>
      <ResponsibleIM>54</ResponsibleIM>
      <TrainType>1</TrainType>
      <TrafficType>11</TrafficType>
      <CommercialTrafficType>84</CommercialTrafficType>
      <TrainActivity>
        <TrainActivityType>0001</TrainActivityType>
      </TrainActivity>
      <OperationalTrainNumber>16872</OperationalTrainNumber>
      <NetworkSpecificParameter>
        <Name>CZPublicService</Name>
        <Value>1</Value>
      </NetworkSpecificParameter>
      <NetworkSpecificParameter>
        <Name>CZPassengerPublicTransportOrderingCoName</Name>
        <Value>Rakovník</Value>
      </NetworkSpecificParameter>
      <NetworkSpecificParameter>
        <Name>CZAlternativeTransport</Name>
        <Value>0</Value>
      </NetworkSpecificParameter>
      <NetworkSpecificParameter>
        <Name>CZPassengerDwellTime</Name>
        <Value>1</Value>
      </NetworkSpecificParameter>
    </CZPTTLocation>
    <CZPTTLocation>
      <Location>
        <CountryCodeISO>CZ</CountryCodeISO>
        <LocationPrimaryCode>53466</LocationPrimaryCode>
        <PrimaryLocationName>Rakovník zastávka</PrimaryLocationName>
      </Location>
      <TimingAtLocation>
        <Timing TimingQualifierCode="ALA">
          <Time>11:53:30.0000000+01:00</Time>
          <Offset>0</Offset>
        </Timing>
        <Timing TimingQualifierCode="ALD">
          <Time>11:53:30.0000000+01:00</Time>
          <Offset>0</Offset>
        </Timing>
      </TimingAtLocation>
      <ResponsibleRU>3736</ResponsibleRU>
      <ResponsibleIM>54</ResponsibleIM>
      <TrainType>1</TrainType>
      <TrafficType>11</TrafficType>
      <CommercialTrafficType>84</CommercialTrafficType>
      <OperationalTrainNumber>16872</OperationalTrainNumber>
      <NetworkSpecificParameter>
        <Name>CZPublicService</Name>
        <Value>1</Value>
      </NetworkSpecificParameter>
      <NetworkSpecificParameter>
        <Name>CZPassengerPublicTransportOrderingCoName</Name>
        <Value>Rakovník</Value>
      </NetworkSpecificParameter>
      <NetworkSpecificParameter>
        <Name>CZAlternativeTransport</Name>
        <Value>0</Value>
      </NetworkSpecificParameter>
    </CZPTTLocation>
    <CZPTTLocation>
      <Location>
        <CountryCodeISO>CZ</CountryCodeISO>
        <LocationPrimaryCode>58423</LocationPrimaryCode>
        <PrimaryLocationName>AHr Hlavačov náv. Lo</PrimaryLocationName>
      </Location>
      <TimingAtLocation>
        <Timing TimingQualifierCode="ALA">
          <Time>11:55:00.0000000+01:00</Time>
          <Offset>0</Offset>
        </Timing>
        <Timing TimingQualifierCode="ALD">
          <Time>11:55:00.0000000+01:00</Time>
          <Offset>0</Offset>
        </Timing>
      </TimingAtLocation>
      <ResponsibleRU>3736</ResponsibleRU>
      <ResponsibleIM>54</ResponsibleIM>
      <TrainType>1</TrainType>
      <TrafficType>11</TrafficType>
      <CommercialTrafficType>84</CommercialTrafficType>
      <OperationalTrainNumber>16872</OperationalTrainNumber>
      <NetworkSpecificParameter>
        <Name>CZPublicService</Name>
        <Value>1</Value>
      </NetworkSpecificParameter>
      <NetworkSpecificParameter>
        <Name>CZPassengerPublicTransportOrderingCoName</Name>
        <Value>Rakovník</Value>
      </NetworkSpecificParameter>
      <NetworkSpecificParameter>
        <Name>CZAlternativeTransport</Name>
        <Value>0</Value>
      </NetworkSpecificParameter>
    </CZPTTLocation>
    <CZPTTLocation>
      <Location>
        <CountryCodeISO>CZ</CountryCodeISO>
        <LocationPrimaryCode>53457</LocationPrimaryCode>
        <PrimaryLocationName>vl. v km 4,700</PrimaryLocationName>
      </Location>
      <TimingAtLocation>
        <Timing TimingQualifierCode="ALA">
          <Time>11:55:30.0000000+01:00</Time>
          <Offset>0</Offset>
        </Timing>
        <Timing TimingQualifierCode="ALD">
          <Time>11:55:30.0000000+01:00</Time>
          <Offset>0</Offset>
        </Timing>
      </TimingAtLocation>
      <ResponsibleRU>3736</ResponsibleRU>
      <ResponsibleIM>54</ResponsibleIM>
      <TrainType>1</TrainType>
      <TrafficType>11</TrafficType>
      <CommercialTrafficType>84</CommercialTrafficType>
      <OperationalTrainNumber>16872</OperationalTrainNumber>
      <NetworkSpecificParameter>
        <Name>CZPublicService</Name>
        <Value>1</Value>
      </NetworkSpecificParameter>
      <NetworkSpecificParameter>
        <Name>CZPassengerPublicTransportOrderingCoName</Name>
        <Value>Rakovník</Value>
      </NetworkSpecificParameter>
      <NetworkSpecificParameter>
        <Name>CZAlternativeTransport</Name>
        <Value>0</Value>
      </NetworkSpecificParameter>
    </CZPTTLocation>
    <CZPTTLocation>
      <Location>
        <CountryCodeISO>CZ</CountryCodeISO>
        <LocationPrimaryCode>58424</LocationPrimaryCode>
        <PrimaryLocationName>AHr Hlavačov náv. So</PrimaryLocationName>
      </Location>
      <TimingAtLocation>
        <Timing TimingQualifierCode="ALA">
          <Time>11:56:00.0000000+01:00</Time>
          <Offset>0</Offset>
        </Timing>
        <Timing TimingQualifierCode="ALD">
          <Time>11:56:00.0000000+01:00</Time>
          <Offset>0</Offset>
        </Timing>
      </TimingAtLocation>
      <ResponsibleRU>3736</ResponsibleRU>
      <ResponsibleIM>54</ResponsibleIM>
      <TrainType>1</TrainType>
      <TrafficType>11</TrafficType>
      <CommercialTrafficType>84</CommercialTrafficType>
      <OperationalTrainNumber>16872</OperationalTrainNumber>
      <NetworkSpecificParameter>
        <Name>CZPublicService</Name>
        <Value>1</Value>
      </NetworkSpecificParameter>
      <NetworkSpecificParameter>
        <Name>CZPassengerPublicTransportOrderingCoName</Name>
        <Value>Rakovník</Value>
      </NetworkSpecificParameter>
      <NetworkSpecificParameter>
        <Name>CZAlternativeTransport</Name>
        <Value>0</Value>
      </NetworkSpecificParameter>
    </CZPTTLocation>
    <CZPTTLocation>
      <Location>
        <CountryCodeISO>CZ</CountryCodeISO>
        <LocationPrimaryCode>53456</LocationPrimaryCode>
        <PrimaryLocationName>Lužná u Rakovníka</PrimaryLocationName>
        <LocationSubsidiaryIdentification>
          <LocationSubsidiaryCode LocationSubsidiaryTypeCode="1">3</LocationSubsidiaryCode>
          <AllocationCompany>0054</AllocationCompany>
        </LocationSubsidiaryIdentification>
      </Location>
      <TimingAtLocation>
        <Timing TimingQualifierCode="ALA">
          <Time>12:01:00.0000000+01:00</Time>
          <Offset>0</Offset>
        </Timing>
        <Timing TimingQualifierCode="ALD">
          <Time>12:04:00.0000000+01:00</Time>
          <Offset>0</Offset>
        </Timing>
        <DwellTime>3</DwellTime>
      </TimingAtLocation>
      <ResponsibleRU>3736</ResponsibleRU>
      <ResponsibleIM>54</ResponsibleIM>
      <TrainType>1</TrainType>
      <TrafficType>11</TrafficType>
      <CommercialTrafficType>84</CommercialTrafficType>
      <TrainActivity>
        <TrainActivityType>0001</TrainActivityType>
      </TrainActivity>
      <OperationalTrainNumber>16872</OperationalTrainNumber>
      <NetworkSpecificParameter>
        <Name>CZPublicService</Name>
        <Value>1</Value>
      </NetworkSpecificParameter>
      <NetworkSpecificParameter>
        <Name>CZPassengerPublicTransportOrderingCoName</Name>
        <Value>Rakovník</Value>
      </NetworkSpecificParameter>
      <NetworkSpecificParameter>
        <Name>CZAlternativeTransport</Name>
        <Value>0</Value>
      </NetworkSpecificParameter>
      <NetworkSpecificParameter>
        <Name>CZPassengerDwellTime</Name>
        <Value>1</Value>
      </NetworkSpecificParameter>
    </CZPTTLocation>
    <CZPTTLocation>
      <Location>
        <CountryCodeISO>CZ</CountryCodeISO>
        <LocationPrimaryCode>53376</LocationPrimaryCode>
        <PrimaryLocationName>Krupá</PrimaryLocationName>
        <LocationSubsidiaryIdentification>
          <LocationSubsidiaryCode LocationSubsidiaryTypeCode="1">3</LocationSubsidiaryCode>
          <AllocationCompany>0054</AllocationCompany>
        </LocationSubsidiaryIdentification>
      </Location>
      <TimingAtLocation>
        <Timing TimingQualifierCode="ALA">
          <Time>12:14:00.0000000+01:00</Time>
          <Offset>0</Offset>
        </Timing>
        <Timing TimingQualifierCode="ALD">
          <Time>12:16:00.0000000+01:00</Time>
          <Offset>0</Offset>
        </Timing>
        <DwellTime>2</DwellTime>
      </TimingAtLocation>
      <ResponsibleRU>3736</ResponsibleRU>
      <ResponsibleIM>54</ResponsibleIM>
      <TrainType>1</TrainType>
      <TrafficType>11</TrafficType>
      <CommercialTrafficType>84</CommercialTrafficType>
      <TrainActivity>
        <TrainActivityType>0001</TrainActivityType>
      </TrainActivity>
      <OperationalTrainNumber>16872</OperationalTrainNumber>
      <NetworkSpecificParameter>
        <Name>CZPublicService</Name>
        <Value>1</Value>
      </NetworkSpecificParameter>
      <NetworkSpecificParameter>
        <Name>CZPassengerPublicTransportOrderingCoName</Name>
        <Value>Rakovník</Value>
      </NetworkSpecificParameter>
      <NetworkSpecificParameter>
        <Name>CZAlternativeTransport</Name>
        <Value>0</Value>
      </NetworkSpecificParameter>
      <NetworkSpecificParameter>
        <Name>CZPassengerDwellTime</Name>
        <Value>1</Value>
      </NetworkSpecificParameter>
    </CZPTTLocation>
    <CZPTTLocation>
      <Location>
        <CountryCodeISO>CZ</CountryCodeISO>
        <LocationPrimaryCode>53436</LocationPrimaryCode>
        <PrimaryLocationName>Olešná u Rakovníka</PrimaryLocationName>
      </Location>
      <TimingAtLocation>
        <Timing TimingQualifierCode="ALA">
          <Time>12:28:30.0000000+01:00</Time>
          <Offset>0</Offset>
        </Timing>
        <Timing TimingQualifierCode="ALD">
          <Time>12:28:30.0000000+01:00</Time>
          <Offset>0</Offset>
        </Timing>
      </TimingAtLocation>
      <ResponsibleRU>3736</ResponsibleRU>
      <ResponsibleIM>54</ResponsibleIM>
      <TrainType>1</TrainType>
      <TrafficType>11</TrafficType>
      <CommercialTrafficType>84</CommercialTrafficType>
      <TrainActivity>
        <TrainActivityType>0001</TrainActivityType>
      </TrainActivity>
      <TrainActivity>
        <TrainActivityType>CZ02</TrainActivityType>
      </TrainActivity>
      <TrainActivity>
        <TrainActivityType>0030</TrainActivityType>
      </TrainActivity>
      <OperationalTrainNumber>16872</OperationalTrainNumber>
      <NetworkSpecificParameter>
        <Name>CZPublicService</Name>
        <Value>1</Value>
      </NetworkSpecificParameter>
      <NetworkSpecificParameter>
        <Name>CZPassengerPublicTransportOrderingCoName</Name>
        <Value>Rakovník</Value>
      </NetworkSpecificParameter>
      <NetworkSpecificParameter>
        <Name>CZAlternativeTransport</Name>
        <Value>0</Value>
      </NetworkSpecificParameter>
      <NetworkSpecificParameter>
        <Name>CZPassengerDwellTime</Name>
        <Value>1</Value>
      </NetworkSpecificParameter>
    </CZPTTLocation>
    <CZPTTLocation>
      <Location>
        <CountryCodeISO>CZ</CountryCodeISO>
        <LocationPrimaryCode>53426</LocationPrimaryCode>
        <PrimaryLocationName>Chrášťany zastávka</PrimaryLocationName>
      </Location>
      <TimingAtLocation>
        <Timing TimingQualifierCode="ALA">
          <Time>12:32:30.0000000+01:00</Time>
          <Offset>0</Offset>
        </Timing>
        <Timing TimingQualifierCode="ALD">
          <Time>12:32:30.0000000+01:00</Time>
          <Offset>0</Offset>
        </Timing>
      </TimingAtLocation>
      <ResponsibleRU>3736</ResponsibleRU>
      <ResponsibleIM>54</ResponsibleIM>
      <TrainType>1</TrainType>
      <TrafficType>11</TrafficType>
      <CommercialTrafficType>84</CommercialTrafficType>
      <TrainActivity>
        <TrainActivityType>0001</TrainActivityType>
      </TrainActivity>
      <TrainActivity>
        <TrainActivityType>CZ02</TrainActivityType>
      </TrainActivity>
      <TrainActivity>
        <TrainActivityType>0030</TrainActivityType>
      </TrainActivity>
      <OperationalTrainNumber>16872</OperationalTrainNumber>
      <NetworkSpecificParameter>
        <Name>CZPublicService</Name>
        <Value>1</Value>
      </NetworkSpecificParameter>
      <NetworkSpecificParameter>
        <Name>CZPassengerPublicTransportOrderingCoName</Name>
        <Value>Rakovník</Value>
      </NetworkSpecificParameter>
      <NetworkSpecificParameter>
        <Name>CZAlternativeTransport</Name>
        <Value>0</Value>
      </NetworkSpecificParameter>
      <NetworkSpecificParameter>
        <Name>CZPassengerDwellTime</Name>
        <Value>1</Value>
      </NetworkSpecificParameter>
    </CZPTTLocation>
    <CZPTTLocation>
      <Location>
        <CountryCodeISO>CZ</CountryCodeISO>
        <LocationPrimaryCode>53416</LocationPrimaryCode>
        <PrimaryLocationName>Kněževes</PrimaryLocationName>
        <LocationSubsidiaryIdentification>
          <LocationSubsidiaryCode LocationSubsidiaryTypeCode="1">1</LocationSubsidiaryCode>
          <AllocationCompany>0054</AllocationCompany>
        </LocationSubsidiaryIdentification>
      </Location>
      <TimingAtLocation>
        <Timing TimingQualifierCode="ALA">
          <Time>12:39:30.0000000+01:00</Time>
          <Offset>0</Offset>
        </Timing>
        <Timing TimingQualifierCode="ALD">
          <Time>12:40:00.0000000+01:00</Time>
          <Offset>0</Offset>
        </Timing>
        <DwellTime>0.5</DwellTime>
      </TimingAtLocation>
      <ResponsibleRU>3736</ResponsibleRU>
      <ResponsibleIM>54</ResponsibleIM>
      <TrainType>1</TrainType>
      <TrafficType>11</TrafficType>
      <CommercialTrafficType>84</CommercialTrafficType>
      <TrainActivity>
        <TrainActivityType>0001</TrainActivityType>
      </TrainActivity>
      <OperationalTrainNumber>16872</OperationalTrainNumber>
      <NetworkSpecificParameter>
        <Name>CZPublicService</Name>
        <Value>1</Value>
      </NetworkSpecificParameter>
      <NetworkSpecificParameter>
        <Name>CZPassengerPublicTransportOrderingCoName</Name>
        <Value>Rakovník</Value>
      </NetworkSpecificParameter>
      <NetworkSpecificParameter>
        <Name>CZAlternativeTransport</Name>
        <Value>0</Value>
      </NetworkSpecificParameter>
      <NetworkSpecificParameter>
        <Name>CZPassengerDwellTime</Name>
        <Value>1</Value>
      </NetworkSpecificParameter>
    </CZPTTLocation>
    <CZPTTLocation>
      <Location>
        <CountryCodeISO>CZ</CountryCodeISO>
        <LocationPrimaryCode>53406</LocationPrimaryCode>
        <PrimaryLocationName>Přílepy</PrimaryLocationName>
      </Location>
      <TimingAtLocation>
        <Timing TimingQualifierCode="ALA">
          <Time>12:41:30.0000000+01:00</Time>
          <Offset>0</Offset>
        </Timing>
        <Timing TimingQualifierCode="ALD">
          <Time>12:41:30.0000000+01:00</Time>
          <Offset>0</Offset>
        </Timing>
      </TimingAtLocation>
      <ResponsibleRU>3736</ResponsibleRU>
      <ResponsibleIM>54</ResponsibleIM>
      <TrainType>1</TrainType>
      <TrafficType>11</TrafficType>
      <CommercialTrafficType>84</CommercialTrafficType>
      <TrainActivity>
        <TrainActivityType>0001</TrainActivityType>
      </TrainActivity>
      <TrainActivity>
        <TrainActivityType>CZ02</TrainActivityType>
      </TrainActivity>
      <TrainActivity>
        <TrainActivityType>0030</TrainActivityType>
      </TrainActivity>
      <OperationalTrainNumber>16872</OperationalTrainNumber>
      <NetworkSpecificParameter>
        <Name>CZPublicService</Name>
        <Value>1</Value>
      </NetworkSpecificParameter>
      <NetworkSpecificParameter>
        <Name>CZPassengerPublicTransportOrderingCoName</Name>
        <Value>Rakovník</Value>
      </NetworkSpecificParameter>
      <NetworkSpecificParameter>
        <Name>CZAlternativeTransport</Name>
        <Value>0</Value>
      </NetworkSpecificParameter>
      <NetworkSpecificParameter>
        <Name>CZPassengerDwellTime</Name>
        <Value>1</Value>
      </NetworkSpecificParameter>
    </CZPTTLocation>
    <CZPTTLocation>
      <Location>
        <CountryCodeISO>CZ</CountryCodeISO>
        <LocationPrimaryCode>53396</LocationPrimaryCode>
        <PrimaryLocationName>Kolešovice</PrimaryLocationName>
        <LocationSubsidiaryIdentification>
          <LocationSubsidiaryCode LocationSubsidiaryTypeCode="1">2</LocationSubsidiaryCode>
          <AllocationCompany>0054</AllocationCompany>
        </LocationSubsidiaryIdentification>
      </Location>
      <TimingAtLocation>
        <Timing TimingQualifierCode="ALA">
          <Time>12:48:00.0000000+01:00</Time>
          <Offset>0</Offset>
        </Timing>
      </TimingAtLocation>
      <ResponsibleRU>3736</ResponsibleRU>
      <ResponsibleIM>54</ResponsibleIM>
      <TrainType>1</TrainType>
      <TrafficType>11</TrafficType>
      <CommercialTrafficType>84</CommercialTrafficType>
      <TrainActivity>
        <TrainActivityType>0001</TrainActivityType>
      </TrainActivity>
      <OperationalTrainNumber>16872</OperationalTrainNumber>
      <NetworkSpecificParameter>
        <Name>CZPublicService</Name>
        <Value>1</Value>
      </NetworkSpecificParameter>
      <NetworkSpecificParameter>
        <Name>CZPassengerPublicTransportOrderingCoName</Name>
        <Value>Rakovník</Value>
      </NetworkSpecificParameter>
      <NetworkSpecificParameter>
        <Name>CZAlternativeTransport</Name>
        <Value>0</Value>
      </NetworkSpecificParameter>
      <NetworkSpecificParameter>
        <Name>CZPassengerDwellTime</Name>
        <Value>1</Value>
      </NetworkSpecificParameter>
    </CZPTTLocation>
    <PlannedCalendar>
      <BitmapDays>1000000000000000000000000000000000000000000000000100000000000000000000000000000000001</BitmapDays>
      <ValidityPeriod>
        <StartDateTime>2026-05-30T00:00:00</StartDateTime>
        <EndDateTime>2026-08-22T00:00:00</EndDateTime>
      </ValidityPeriod>
    </PlannedCalendar>
  </CZPTTInformation>
  <NetworkSpecificParameter>
    <Name>CZCentralPTTNote</Name>
    <Value>37|CZ76094||CZ53396||0|</Value>
  </NetworkSpecificParameter>
  <NetworkSpecificParameter>
    <Name>CZNonCentralPTTNote</Name>
    <Value>CZ76094||CZ53396||neplatí tarify integrovaných dopravních systémů, jízdné dle tarifu dopravce|2|3|0|0|</Value>
  </NetworkSpecificParameter>
</CZPTTCISMessage>