<?xml version="1.0"?>
<CZPTTCISMessage xmlns:xsd="http://www.w3.org/2001/XMLSchema" xmlns:xsi="http://www.w3.org/2001/XMLSchema-instance">
  <Identifiers>
    <PlannedTransportIdentifiers>
      <ObjectType>PA</ObjectType>
      <Company>0054</Company>
      <Core>KT-----4625A</Core>
      <Variant>00</Variant>
      <TimetableYear>2026</TimetableYear>
    </PlannedTransportIdentifiers>
    <PlannedTransportIdentifiers>
      <ObjectType>TR</ObjectType>
      <Company>1154</Company>
      <Core>KASO--456701</Core>
      <Variant>00</Variant>
      <TimetableYear>2026</TimetableYear>
    </PlannedTransportIdentifiers>
  </Identifiers>
  <CZPTTCreation>2025-11-06T17:09:33</CZPTTCreation>
  <CZPTTHeader />
  <CZPTTInformation>
    <CZPTTLocation>
      <Location>
        <CountryCodeISO>CZ</CountryCodeISO>
        <LocationPrimaryCode>53066</LocationPrimaryCode>
        <PrimaryLocationName>Český Brod</PrimaryLocationName>
        <LocationSubsidiaryIdentification>
          <LocationSubsidiaryCode LocationSubsidiaryTypeCode="1">3</LocationSubsidiaryCode>
          <AllocationCompany>0054</AllocationCompany>
        </LocationSubsidiaryIdentification>
      </Location>
      <TimingAtLocation>
        <Timing TimingQualifierCode="ALD">
          <Time>08:52:00.0000000+01:00</Time>
          <Offset>0</Offset>
        </Timing>
      </TimingAtLocation>
      <ResponsibleRU>1154</ResponsibleRU>
      <ResponsibleIM>54</ResponsibleIM>
      <TrainType>1</TrainType>
      <TrafficType>11</TrafficType>
      <CommercialTrafficType>84</CommercialTrafficType>
      <TrainActivity>
        <TrainActivityType>0001</TrainActivityType>
      </TrainActivity>
      <TrainActivity>
        <TrainActivityType>0033</TrainActivityType>
      </TrainActivity>
      <OperationalTrainNumber>8614</OperationalTrainNumber>
      <NetworkSpecificParameter>
        <Name>CZPassengerServiceNumber</Name>
        <Value>1001</Value>
      </NetworkSpecificParameter>
      <NetworkSpecificParameter>
        <Name>CZPublicService</Name>
        <Value>1</Value>
      </NetworkSpecificParameter>
      <NetworkSpecificParameter>
        <Name>CZPassengerPublicTransportOrderingCoName</Name>
        <Value>Středočeský kraj</Value>
      </NetworkSpecificParameter>
      <NetworkSpecificParameter>
        <Name>CZAlternativeTransport</Name>
        <Value>0</Value>
      </NetworkSpecificParameter>
      <NetworkSpecificParameter>
        <Name>CZPassengerDwellTime</Name>
        <Value>1</Value>
      </NetworkSpecificParameter>
    </CZPTTLocation>
    <CZPTTLocation>
      <Location>
        <CountryCodeISO>CZ</CountryCodeISO>
        <LocationPrimaryCode>53086</LocationPrimaryCode>
        <PrimaryLocationName>Rostoklaty</PrimaryLocationName>
      </Location>
      <TimingAtLocation>
        <Timing TimingQualifierCode="ALA">
          <Time>08:56:00.0000000+01:00</Time>
          <Offset>0</Offset>
        </Timing>
        <Timing TimingQualifierCode="ALD">
          <Time>08:56:30.0000000+01:00</Time>
          <Offset>0</Offset>
        </Timing>
        <DwellTime>0.5</DwellTime>
      </TimingAtLocation>
      <ResponsibleRU>1154</ResponsibleRU>
      <ResponsibleIM>54</ResponsibleIM>
      <TrainType>1</TrainType>
      <TrafficType>11</TrafficType>
      <CommercialTrafficType>84</CommercialTrafficType>
      <TrainActivity>
        <TrainActivityType>0001</TrainActivityType>
      </TrainActivity>
      <TrainActivity>
        <TrainActivityType>0033</TrainActivityType>
      </TrainActivity>
      <OperationalTrainNumber>8614</OperationalTrainNumber>
      <NetworkSpecificParameter>
        <Name>CZPassengerServiceNumber</Name>
        <Value>1001</Value>
      </NetworkSpecificParameter>
      <NetworkSpecificParameter>
        <Name>CZPublicService</Name>
        <Value>1</Value>
      </NetworkSpecificParameter>
      <NetworkSpecificParameter>
        <Name>CZPassengerPublicTransportOrderingCoName</Name>
        <Value>Středočeský kraj</Value>
      </NetworkSpecificParameter>
      <NetworkSpecificParameter>
        <Name>CZAlternativeTransport</Name>
        <Value>0</Value>
      </NetworkSpecificParameter>
      <NetworkSpecificParameter>
        <Name>CZPassengerDwellTime</Name>
        <Value>1</Value>
      </NetworkSpecificParameter>
    </CZPTTLocation>
    <CZPTTLocation>
      <Location>
        <CountryCodeISO>CZ</CountryCodeISO>
        <LocationPrimaryCode>53076</LocationPrimaryCode>
        <PrimaryLocationName>Tuklaty</PrimaryLocationName>
      </Location>
      <TimingAtLocation>
        <Timing TimingQualifierCode="ALA">
          <Time>08:59:00.0000000+01:00</Time>
          <Offset>0</Offset>
        </Timing>
        <Timing TimingQualifierCode="ALD">
          <Time>08:59:30.0000000+01:00</Time>
          <Offset>0</Offset>
        </Timing>
        <DwellTime>0.5</DwellTime>
      </TimingAtLocation>
      <ResponsibleRU>1154</ResponsibleRU>
      <ResponsibleIM>54</ResponsibleIM>
      <TrainType>1</TrainType>
      <TrafficType>11</TrafficType>
      <CommercialTrafficType>84</CommercialTrafficType>
      <TrainActivity>
        <TrainActivityType>0001</TrainActivityType>
      </TrainActivity>
      <TrainActivity>
        <TrainActivityType>0033</TrainActivityType>
      </TrainActivity>
      <OperationalTrainNumber>8614</OperationalTrainNumber>
      <NetworkSpecificParameter>
        <Name>CZPassengerServiceNumber</Name>
        <Value>1001</Value>
      </NetworkSpecificParameter>
      <NetworkSpecificParameter>
        <Name>CZPublicService</Name>
        <Value>1</Value>
      </NetworkSpecificParameter>
      <NetworkSpecificParameter>
        <Name>CZPassengerPublicTransportOrderingCoName</Name>
        <Value>Středočeský kraj</Value>
      </NetworkSpecificParameter>
      <NetworkSpecificParameter>
        <Name>CZAlternativeTransport</Name>
        <Value>0</Value>
      </NetworkSpecificParameter>
      <NetworkSpecificParameter>
        <Name>CZPassengerDwellTime</Name>
        <Value>1</Value>
      </NetworkSpecificParameter>
    </CZPTTLocation>
    <CZPTTLocation>
      <Location>
        <CountryCodeISO>CZ</CountryCodeISO>
        <LocationPrimaryCode>53046</LocationPrimaryCode>
        <PrimaryLocationName>Úvaly</PrimaryLocationName>
        <LocationSubsidiaryIdentification>
          <LocationSubsidiaryCode LocationSubsidiaryTypeCode="1">2</LocationSubsidiaryCode>
          <AllocationCompany>0054</AllocationCompany>
        </LocationSubsidiaryIdentification>
      </Location>
      <TimingAtLocation>
        <Timing TimingQualifierCode="ALA">
          <Time>09:02:30.0000000+01:00</Time>
          <Offset>0</Offset>
        </Timing>
        <Timing TimingQualifierCode="ALD">
          <Time>09:03:00.0000000+01:00</Time>
          <Offset>0</Offset>
        </Timing>
        <DwellTime>0.5</DwellTime>
      </TimingAtLocation>
      <ResponsibleRU>1154</ResponsibleRU>
      <ResponsibleIM>54</ResponsibleIM>
      <TrainType>1</TrainType>
      <TrafficType>11</TrafficType>
      <CommercialTrafficType>84</CommercialTrafficType>
      <TrainActivity>
        <TrainActivityType>0001</TrainActivityType>
      </TrainActivity>
      <TrainActivity>
        <TrainActivityType>0033</TrainActivityType>
      </TrainActivity>
      <OperationalTrainNumber>8614</OperationalTrainNumber>
      <NetworkSpecificParameter>
        <Name>CZPassengerServiceNumber</Name>
        <Value>1001</Value>
      </NetworkSpecificParameter>
      <NetworkSpecificParameter>
        <Name>CZPublicService</Name>
        <Value>1</Value>
      </NetworkSpecificParameter>
      <NetworkSpecificParameter>
        <Name>CZPassengerPublicTransportOrderingCoName</Name>
        <Value>Středočeský kraj</Value>
      </NetworkSpecificParameter>
      <NetworkSpecificParameter>
        <Name>CZAlternativeTransport</Name>
        <Value>0</Value>
      </NetworkSpecificParameter>
      <NetworkSpecificParameter>
        <Name>CZPassengerDwellTime</Name>
        <Value>1</Value>
      </NetworkSpecificParameter>
    </CZPTTLocation>
    <CZPTTLocation>
      <Location>
        <CountryCodeISO>CZ</CountryCodeISO>
        <LocationPrimaryCode>53047</LocationPrimaryCode>
        <PrimaryLocationName>hr.VUSC 0100/0200 04</PrimaryLocationName>
      </Location>
      <TimingAtLocation>
        <Timing TimingQualifierCode="ALA">
          <Time>09:04:30.0000000+01:00</Time>
          <Offset>0</Offset>
        </Timing>
        <Timing TimingQualifierCode="ALD">
          <Time>09:04:30.0000000+01:00</Time>
          <Offset>0</Offset>
        </Timing>
      </TimingAtLocation>
      <ResponsibleRU>1154</ResponsibleRU>
      <ResponsibleIM>54</ResponsibleIM>
      <TrainType>1</TrainType>
      <TrafficType>11</TrafficType>
      <CommercialTrafficType>84</CommercialTrafficType>
      <OperationalTrainNumber>8614</OperationalTrainNumber>
      <NetworkSpecificParameter>
        <Name>CZPassengerServiceNumber</Name>
        <Value>1001</Value>
      </NetworkSpecificParameter>
      <NetworkSpecificParameter>
        <Name>CZPublicService</Name>
        <Value>1</Value>
      </NetworkSpecificParameter>
      <NetworkSpecificParameter>
        <Name>CZPassengerPublicTransportOrderingCoName</Name>
        <Value>Hlavní město Praha</Value>
      </NetworkSpecificParameter>
      <NetworkSpecificParameter>
        <Name>CZAlternativeTransport</Name>
        <Value>0</Value>
      </NetworkSpecificParameter>
    </CZPTTLocation>
    <CZPTTLocation>
      <Location>
        <CountryCodeISO>CZ</CountryCodeISO>
        <LocationPrimaryCode>53056</LocationPrimaryCode>
        <PrimaryLocationName>Praha-Klánovice</PrimaryLocationName>
      </Location>
      <TimingAtLocation>
        <Timing TimingQualifierCode="ALA">
          <Time>09:06:30.0000000+01:00</Time>
          <Offset>0</Offset>
        </Timing>
        <Timing TimingQualifierCode="ALD">
          <Time>09:07:00.0000000+01:00</Time>
          <Offset>0</Offset>
        </Timing>
        <DwellTime>0.5</DwellTime>
      </TimingAtLocation>
      <ResponsibleRU>1154</ResponsibleRU>
      <ResponsibleIM>54</ResponsibleIM>
      <TrainType>1</TrainType>
      <TrafficType>11</TrafficType>
      <CommercialTrafficType>84</CommercialTrafficType>
      <TrainActivity>
        <TrainActivityType>0001</TrainActivityType>
      </TrainActivity>
      <TrainActivity>
        <TrainActivityType>0033</TrainActivityType>
      </TrainActivity>
      <OperationalTrainNumber>8614</OperationalTrainNumber>
      <NetworkSpecificParameter>
        <Name>CZPassengerServiceNumber</Name>
        <Value>1001</Value>
      </NetworkSpecificParameter>
      <NetworkSpecificParameter>
        <Name>CZPublicService</Name>
        <Value>1</Value>
      </NetworkSpecificParameter>
      <NetworkSpecificParameter>
        <Name>CZPassengerPublicTransportOrderingCoName</Name>
        <Value>Hlavní město Praha</Value>
      </NetworkSpecificParameter>
      <NetworkSpecificParameter>
        <Name>CZAlternativeTransport</Name>
        <Value>0</Value>
      </NetworkSpecificParameter>
      <NetworkSpecificParameter>
        <Name>CZPassengerDwellTime</Name>
        <Value>1</Value>
      </NetworkSpecificParameter>
    </CZPTTLocation>
    <CZPTTLocation>
      <Location>
        <CountryCodeISO>CZ</CountryCodeISO>
        <LocationPrimaryCode>58066</LocationPrimaryCode>
        <PrimaryLocationName>Blatov odbočka</PrimaryLocationName>
        <LocationSubsidiaryIdentification>
          <LocationSubsidiaryCode LocationSubsidiaryTypeCode="1">2a</LocationSubsidiaryCode>
          <AllocationCompany>0054</AllocationCompany>
        </LocationSubsidiaryIdentification>
      </Location>
      <TimingAtLocation>
        <Timing TimingQualifierCode="ALA">
          <Time>09:09:00.0000000+01:00</Time>
          <Offset>0</Offset>
        </Timing>
        <Timing TimingQualifierCode="ALD">
          <Time>09:09:00.0000000+01:00</Time>
          <Offset>0</Offset>
        </Timing>
      </TimingAtLocation>
      <ResponsibleRU>1154</ResponsibleRU>
      <ResponsibleIM>54</ResponsibleIM>
      <TrainType>1</TrainType>
      <TrafficType>11</TrafficType>
      <CommercialTrafficType>84</CommercialTrafficType>
      <OperationalTrainNumber>8614</OperationalTrainNumber>
      <NetworkSpecificParameter>
        <Name>CZPassengerServiceNumber</Name>
        <Value>1001</Value>
      </NetworkSpecificParameter>
      <NetworkSpecificParameter>
        <Name>CZPublicService</Name>
        <Value>1</Value>
      </NetworkSpecificParameter>
      <NetworkSpecificParameter>
        <Name>CZPassengerPublicTransportOrderingCoName</Name>
        <Value>Hlavní město Praha</Value>
      </NetworkSpecificParameter>
      <NetworkSpecificParameter>
        <Name>CZAlternativeTransport</Name>
        <Value>0</Value>
      </NetworkSpecificParameter>
    </CZPTTLocation>
    <CZPTTLocation>
      <Location>
        <CountryCodeISO>CZ</CountryCodeISO>
        <LocationPrimaryCode>53006</LocationPrimaryCode>
        <PrimaryLocationName>Praha-Běchovice střed</PrimaryLocationName>
        <LocationSubsidiaryIdentification>
          <LocationSubsidiaryCode LocationSubsidiaryTypeCode="1">2b</LocationSubsidiaryCode>
          <AllocationCompany>0054</AllocationCompany>
        </LocationSubsidiaryIdentification>
      </Location>
      <TimingAtLocation>
        <Timing TimingQualifierCode="ALA">
          <Time>09:10:00.0000000+01:00</Time>
          <Offset>0</Offset>
        </Timing>
        <Timing TimingQualifierCode="ALD">
          <Time>09:10:30.0000000+01:00</Time>
          <Offset>0</Offset>
        </Timing>
        <DwellTime>0.5</DwellTime>
      </TimingAtLocation>
      <ResponsibleRU>1154</ResponsibleRU>
      <ResponsibleIM>54</ResponsibleIM>
      <TrainType>1</TrainType>
      <TrafficType>11</TrafficType>
      <CommercialTrafficType>84</CommercialTrafficType>
      <TrainActivity>
        <TrainActivityType>0001</TrainActivityType>
      </TrainActivity>
      <TrainActivity>
        <TrainActivityType>0033</TrainActivityType>
      </TrainActivity>
      <OperationalTrainNumber>8614</OperationalTrainNumber>
      <NetworkSpecificParameter>
        <Name>CZPassengerServiceNumber</Name>
        <Value>1001</Value>
      </NetworkSpecificParameter>
      <NetworkSpecificParameter>
        <Name>CZPublicService</Name>
        <Value>1</Value>
      </NetworkSpecificParameter>
      <NetworkSpecificParameter>
        <Name>CZPassengerPublicTransportOrderingCoName</Name>
        <Value>Hlavní město Praha</Value>
      </NetworkSpecificParameter>
      <NetworkSpecificParameter>
        <Name>CZAlternativeTransport</Name>
        <Value>0</Value>
      </NetworkSpecificParameter>
      <NetworkSpecificParameter>
        <Name>CZPassengerDwellTime</Name>
        <Value>1</Value>
      </NetworkSpecificParameter>
    </CZPTTLocation>
    <CZPTTLocation>
      <Location>
        <CountryCodeISO>CZ</CountryCodeISO>
        <LocationPrimaryCode>53016</LocationPrimaryCode>
        <PrimaryLocationName>Praha-Běchovice</PrimaryLocationName>
        <LocationSubsidiaryIdentification>
          <LocationSubsidiaryCode LocationSubsidiaryTypeCode="1">2</LocationSubsidiaryCode>
          <AllocationCompany>0054</AllocationCompany>
        </LocationSubsidiaryIdentification>
      </Location>
      <TimingAtLocation>
        <Timing TimingQualifierCode="ALA">
          <Time>09:12:00.0000000+01:00</Time>
          <Offset>0</Offset>
        </Timing>
        <Timing TimingQualifierCode="ALD">
          <Time>09:12:30.0000000+01:00</Time>
          <Offset>0</Offset>
        </Timing>
        <DwellTime>0.5</DwellTime>
      </TimingAtLocation>
      <ResponsibleRU>1154</ResponsibleRU>
      <ResponsibleIM>54</ResponsibleIM>
      <TrainType>1</TrainType>
      <TrafficType>11</TrafficType>
      <CommercialTrafficType>84</CommercialTrafficType>
      <TrainActivity>
        <TrainActivityType>0001</TrainActivityType>
      </TrainActivity>
      <TrainActivity>
        <TrainActivityType>0033</TrainActivityType>
      </TrainActivity>
      <OperationalTrainNumber>8614</OperationalTrainNumber>
      <NetworkSpecificParameter>
        <Name>CZPassengerServiceNumber</Name>
        <Value>1001</Value>
      </NetworkSpecificParameter>
      <NetworkSpecificParameter>
        <Name>CZPublicService</Name>
        <Value>1</Value>
      </NetworkSpecificParameter>
      <NetworkSpecificParameter>
        <Name>CZPassengerPublicTransportOrderingCoName</Name>
        <Value>Hlavní město Praha</Value>
      </NetworkSpecificParameter>
      <NetworkSpecificParameter>
        <Name>CZAlternativeTransport</Name>
        <Value>0</Value>
      </NetworkSpecificParameter>
      <NetworkSpecificParameter>
        <Name>CZPassengerDwellTime</Name>
        <Value>1</Value>
      </NetworkSpecificParameter>
    </CZPTTLocation>
    <CZPTTLocation>
      <Location>
        <CountryCodeISO>CZ</CountryCodeISO>
        <LocationPrimaryCode>53036</LocationPrimaryCode>
        <PrimaryLocationName>Praha-Dolní Počernice</PrimaryLocationName>
      </Location>
      <TimingAtLocation>
        <Timing TimingQualifierCode="ALA">
          <Time>09:14:30.0000000+01:00</Time>
          <Offset>0</Offset>
        </Timing>
        <Timing TimingQualifierCode="ALD">
          <Time>09:15:00.0000000+01:00</Time>
          <Offset>0</Offset>
        </Timing>
        <DwellTime>0.5</DwellTime>
      </TimingAtLocation>
      <ResponsibleRU>1154</ResponsibleRU>
      <ResponsibleIM>54</ResponsibleIM>
      <TrainType>1</TrainType>
      <TrafficType>11</TrafficType>
      <CommercialTrafficType>84</CommercialTrafficType>
      <TrainActivity>
        <TrainActivityType>0001</TrainActivityType>
      </TrainActivity>
      <TrainActivity>
        <TrainActivityType>0033</TrainActivityType>
      </TrainActivity>
      <OperationalTrainNumber>8614</OperationalTrainNumber>
      <NetworkSpecificParameter>
        <Name>CZPassengerServiceNumber</Name>
        <Value>1001</Value>
      </NetworkSpecificParameter>
      <NetworkSpecificParameter>
        <Name>CZPublicService</Name>
        <Value>1</Value>
      </NetworkSpecificParameter>
      <NetworkSpecificParameter>
        <Name>CZPassengerPublicTransportOrderingCoName</Name>
        <Value>Hlavní město Praha</Value>
      </NetworkSpecificParameter>
      <NetworkSpecificParameter>
        <Name>CZAlternativeTransport</Name>
        <Value>0</Value>
      </NetworkSpecificParameter>
      <NetworkSpecificParameter>
        <Name>CZPassengerDwellTime</Name>
        <Value>1</Value>
      </NetworkSpecificParameter>
    </CZPTTLocation>
    <CZPTTLocation>
      <Location>
        <CountryCodeISO>CZ</CountryCodeISO>
        <LocationPrimaryCode>57366</LocationPrimaryCode>
        <PrimaryLocationName>Praha-Kyje</PrimaryLocationName>
      </Location>
      <TimingAtLocation>
        <Timing TimingQualifierCode="ALA">
          <Time>09:17:00.0000000+01:00</Time>
          <Offset>0</Offset>
        </Timing>
        <Timing TimingQualifierCode="ALD">
          <Time>09:17:30.0000000+01:00</Time>
          <Offset>0</Offset>
        </Timing>
        <DwellTime>0.5</DwellTime>
      </TimingAtLocation>
      <ResponsibleRU>1154</ResponsibleRU>
      <ResponsibleIM>54</ResponsibleIM>
      <TrainType>1</TrainType>
      <TrafficType>11</TrafficType>
      <CommercialTrafficType>84</CommercialTrafficType>
      <TrainActivity>
        <TrainActivityType>0001</TrainActivityType>
      </TrainActivity>
      <TrainActivity>
        <TrainActivityType>0033</TrainActivityType>
      </TrainActivity>
      <OperationalTrainNumber>8614</OperationalTrainNumber>
      <NetworkSpecificParameter>
        <Name>CZPassengerServiceNumber</Name>
        <Value>1001</Value>
      </NetworkSpecificParameter>
      <NetworkSpecificParameter>
        <Name>CZPublicService</Name>
        <Value>1</Value>
      </NetworkSpecificParameter>
      <NetworkSpecificParameter>
        <Name>CZPassengerPublicTransportOrderingCoName</Name>
        <Value>Hlavní město Praha</Value>
      </NetworkSpecificParameter>
      <NetworkSpecificParameter>
        <Name>CZAlternativeTransport</Name>
        <Value>0</Value>
      </NetworkSpecificParameter>
      <NetworkSpecificParameter>
        <Name>CZPassengerDwellTime</Name>
        <Value>1</Value>
      </NetworkSpecificParameter>
    </CZPTTLocation>
    <CZPTTLocation>
      <Location>
        <CountryCodeISO>CZ</CountryCodeISO>
        <LocationPrimaryCode>57176</LocationPrimaryCode>
        <PrimaryLocationName>Praha-Libeň</PrimaryLocationName>
        <LocationSubsidiaryIdentification>
          <LocationSubsidiaryCode LocationSubsidiaryTypeCode="1">2</LocationSubsidiaryCode>
          <AllocationCompany>0054</AllocationCompany>
        </LocationSubsidiaryIdentification>
      </Location>
      <TimingAtLocation>
        <Timing TimingQualifierCode="ALA">
          <Time>09:21:00.0000000+01:00</Time>
          <Offset>0</Offset>
        </Timing>
        <Timing TimingQualifierCode="ALD">
          <Time>09:22:00.0000000+01:00</Time>
          <Offset>0</Offset>
        </Timing>
        <DwellTime>1</DwellTime>
      </TimingAtLocation>
      <ResponsibleRU>1154</ResponsibleRU>
      <ResponsibleIM>54</ResponsibleIM>
      <TrainType>1</TrainType>
      <TrafficType>11</TrafficType>
      <CommercialTrafficType>84</CommercialTrafficType>
      <TrainActivity>
        <TrainActivityType>0001</TrainActivityType>
      </TrainActivity>
      <TrainActivity>
        <TrainActivityType>0033</TrainActivityType>
      </TrainActivity>
      <OperationalTrainNumber>8614</OperationalTrainNumber>
      <NetworkSpecificParameter>
        <Name>CZPassengerServiceNumber</Name>
        <Value>1001</Value>
      </NetworkSpecificParameter>
      <NetworkSpecificParameter>
        <Name>CZPublicService</Name>
        <Value>1</Value>
      </NetworkSpecificParameter>
      <NetworkSpecificParameter>
        <Name>CZPassengerPublicTransportOrderingCoName</Name>
        <Value>Hlavní město Praha</Value>
      </NetworkSpecificParameter>
      <NetworkSpecificParameter>
        <Name>CZAlternativeTransport</Name>
        <Value>0</Value>
      </NetworkSpecificParameter>
      <NetworkSpecificParameter>
        <Name>CZPassengerDwellTime</Name>
        <Value>1</Value>
      </NetworkSpecificParameter>
    </CZPTTLocation>
    <CZPTTLocation>
      <Location>
        <CountryCodeISO>CZ</CountryCodeISO>
        <LocationPrimaryCode>58321</LocationPrimaryCode>
        <PrimaryLocationName>Praha M.n.-Sluncová</PrimaryLocationName>
      </Location>
      <TimingAtLocation>
        <Timing TimingQualifierCode="ALA">
          <Time>09:25:00.0000000+01:00</Time>
          <Offset>0</Offset>
        </Timing>
        <Timing TimingQualifierCode="ALD">
          <Time>09:25:00.0000000+01:00</Time>
          <Offset>0</Offset>
        </Timing>
      </TimingAtLocation>
      <ResponsibleRU>1154</ResponsibleRU>
      <ResponsibleIM>54</ResponsibleIM>
      <TrainType>1</TrainType>
      <TrafficType>11</TrafficType>
      <CommercialTrafficType>84</CommercialTrafficType>
      <OperationalTrainNumber>8614</OperationalTrainNumber>
      <NetworkSpecificParameter>
        <Name>CZPassengerServiceNumber</Name>
        <Value>1001</Value>
      </NetworkSpecificParameter>
      <NetworkSpecificParameter>
        <Name>CZPublicService</Name>
        <Value>1</Value>
      </NetworkSpecificParameter>
      <NetworkSpecificParameter>
        <Name>CZPassengerPublicTransportOrderingCoName</Name>
        <Value>Hlavní město Praha</Value>
      </NetworkSpecificParameter>
      <NetworkSpecificParameter>
        <Name>CZAlternativeTransport</Name>
        <Value>0</Value>
      </NetworkSpecificParameter>
    </CZPTTLocation>
    <CZPTTLocation>
      <Location>
        <CountryCodeISO>CZ</CountryCodeISO>
        <LocationPrimaryCode>58396</LocationPrimaryCode>
        <PrimaryLocationName>Praha Masarykovo nádraží-Hrabovka</PrimaryLocationName>
        <LocationSubsidiaryIdentification>
          <LocationSubsidiaryCode LocationSubsidiaryTypeCode="1">102</LocationSubsidiaryCode>
          <AllocationCompany>0054</AllocationCompany>
        </LocationSubsidiaryIdentification>
      </Location>
      <TimingAtLocation>
        <Timing TimingQualifierCode="ALA">
          <Time>09:27:00.0000000+01:00</Time>
          <Offset>0</Offset>
        </Timing>
        <Timing TimingQualifierCode="ALD">
          <Time>09:27:00.0000000+01:00</Time>
          <Offset>0</Offset>
        </Timing>
      </TimingAtLocation>
      <ResponsibleRU>1154</ResponsibleRU>
      <ResponsibleIM>54</ResponsibleIM>
      <TrainType>1</TrainType>
      <TrafficType>11</TrafficType>
      <CommercialTrafficType>84</CommercialTrafficType>
      <OperationalTrainNumber>8614</OperationalTrainNumber>
      <NetworkSpecificParameter>
        <Name>CZPassengerServiceNumber</Name>
        <Value>1001</Value>
      </NetworkSpecificParameter>
      <NetworkSpecificParameter>
        <Name>CZPublicService</Name>
        <Value>1</Value>
      </NetworkSpecificParameter>
      <NetworkSpecificParameter>
        <Name>CZPassengerPublicTransportOrderingCoName</Name>
        <Value>Hlavní město Praha</Value>
      </NetworkSpecificParameter>
      <NetworkSpecificParameter>
        <Name>CZAlternativeTransport</Name>
        <Value>0</Value>
      </NetworkSpecificParameter>
    </CZPTTLocation>
    <CZPTTLocation>
      <Location>
        <CountryCodeISO>CZ</CountryCodeISO>
        <LocationPrimaryCode>57236</LocationPrimaryCode>
        <PrimaryLocationName>Praha Masaryk. n.</PrimaryLocationName>
        <LocationSubsidiaryIdentification>
          <LocationSubsidiaryCode LocationSubsidiaryTypeCode="1">2</LocationSubsidiaryCode>
          <AllocationCompany>0054</AllocationCompany>
        </LocationSubsidiaryIdentification>
      </Location>
      <TimingAtLocation>
        <Timing TimingQualifierCode="ALA">
          <Time>09:28:00.0000000+01:00</Time>
          <Offset>0</Offset>
        </Timing>
      </TimingAtLocation>
      <ResponsibleRU>1154</ResponsibleRU>
      <ResponsibleIM>54</ResponsibleIM>
      <TrainType>1</TrainType>
      <TrafficType>11</TrafficType>
      <CommercialTrafficType>84</CommercialTrafficType>
      <TrainActivity>
        <TrainActivityType>0001</TrainActivityType>
      </TrainActivity>
      <OperationalTrainNumber>8614</OperationalTrainNumber>
      <NetworkSpecificParameter>
        <Name>CZPassengerServiceNumber</Name>
        <Value>1001</Value>
      </NetworkSpecificParameter>
      <NetworkSpecificParameter>
        <Name>CZPublicService</Name>
        <Value>1</Value>
      </NetworkSpecificParameter>
      <NetworkSpecificParameter>
        <Name>CZPassengerPublicTransportOrderingCoName</Name>
        <Value>Hlavní město Praha</Value>
      </NetworkSpecificParameter>
      <NetworkSpecificParameter>
        <Name>CZAlternativeTransport</Name>
        <Value>0</Value>
      </NetworkSpecificParameter>
    </CZPTTLocation>
    <PlannedCalendar>
      <BitmapDays>11111001100000111010011111001111100111110011111001111100111110011111001111100111110011111001111100111110011110000111100111110011111001111000111100011111001111100111110011111001111100111110011111001111100011110011111001111100111110011111001111100111110011111001111100111110011111001111100011110011111001111100111110011011001111100111110010111001111100111110011111</BitmapDays>
      <ValidityPeriod>
        <StartDateTime>2025-12-15T00:00:00</StartDateTime>
        <EndDateTime>2026-12-11T00:00:00</EndDateTime>
      </ValidityPeriod>
    </PlannedCalendar>
  </CZPTTInformation>
  <NetworkSpecificParameter>
    <Name>CZIPTS</Name>
    <Value>23|CZ53066||CZ53086||</Value>
  </NetworkSpecificParameter>
  <NetworkSpecificParameter>
    <Name>CZIPTS</Name>
    <Value>22|CZ53086||CZ53076||</Value>
  </NetworkSpecificParameter>
  <NetworkSpecificParameter>
    <Name>CZIPTS</Name>
    <Value>20|CZ53066||CZ53047||</Value>
  </NetworkSpecificParameter>
  <NetworkSpecificParameter>
    <Name>CZIPTS</Name>
    <Value>21|CZ53076||CZ53047||</Value>
  </NetworkSpecificParameter>
  <NetworkSpecificParameter>
    <Name>CZIPTS</Name>
    <Value>12|CZ53047||CZ58066||</Value>
  </NetworkSpecificParameter>
  <NetworkSpecificParameter>
    <Name>CZIPTS</Name>
    <Value>13|CZ58066||CZ58321||</Value>
  </NetworkSpecificParameter>
  <NetworkSpecificParameter>
    <Name>CZIPTS</Name>
    <Value>10|CZ53047||CZ57236||</Value>
  </NetworkSpecificParameter>
  <NetworkSpecificParameter>
    <Name>CZIPTS</Name>
    <Value>11|CZ58321||CZ57236||</Value>
  </NetworkSpecificParameter>
  <NetworkSpecificParameter>
    <Name>CZCentralPTTNote</Name>
    <Value>22|CZ53066||CZ57236||0|</Value>
  </NetworkSpecificParameter>
  <NetworkSpecificParameter>
    <Name>CZCentralPTTNote</Name>
    <Value>34|CZ53066||CZ57236||0|</Value>
  </NetworkSpecificParameter>
  <NetworkSpecificParameter>
    <Name>CZCentralPTTNote</Name>
    <Value>10|CZ53066||CZ57236||0|</Value>
  </NetworkSpecificParameter>
  <NetworkSpecificParameter>
    <Name>CZCentralPTTNote</Name>
    <Value>40|CZ53066||CZ57236||0|</Value>
  </NetworkSpecificParameter>
  <NetworkSpecificParameter>
    <Name>CZCentralPTTNote</Name>
    <Value>30|CZ53066||CZ57236||0|</Value>
  </NetworkSpecificParameter>
</CZPTTCISMessage>