<?xml version="1.0"?>
<CZPTTCISMessage xmlns:xsd="http://www.w3.org/2001/XMLSchema" xmlns:xsi="http://www.w3.org/2001/XMLSchema-instance">
  <Identifiers>
    <PlannedTransportIdentifiers>
      <ObjectType>PA</ObjectType>
      <Company>0054</Company>
      <Core>KT----52309A</Core>
      <Variant>00</Variant>
      <TimetableYear>2026</TimetableYear>
    </PlannedTransportIdentifiers>
    <PlannedTransportIdentifiers>
      <ObjectType>TR</ObjectType>
      <Company>1154</Company>
      <Core>KASO--214901</Core>
      <Variant>00</Variant>
      <TimetableYear>2026</TimetableYear>
    </PlannedTransportIdentifiers>
  </Identifiers>
  <CZPTTCreation>2025-11-08T22:46:50</CZPTTCreation>
  <CZPTTHeader />
  <CZPTTInformation>
    <CZPTTLocation>
      <Location>
        <CountryCodeISO>CZ</CountryCodeISO>
        <LocationPrimaryCode>34306</LocationPrimaryCode>
        <PrimaryLocationName>Kojetín</PrimaryLocationName>
        <LocationSubsidiaryIdentification>
          <LocationSubsidiaryCode LocationSubsidiaryTypeCode="1">4</LocationSubsidiaryCode>
          <AllocationCompany>0054</AllocationCompany>
        </LocationSubsidiaryIdentification>
      </Location>
      <TimingAtLocation>
        <Timing TimingQualifierCode="ALD">
          <Time>10:03:00.0000000+01:00</Time>
          <Offset>0</Offset>
        </Timing>
      </TimingAtLocation>
      <ResponsibleRU>1154</ResponsibleRU>
      <ResponsibleIM>54</ResponsibleIM>
      <TrainType>1</TrainType>
      <TrafficType>11</TrafficType>
      <CommercialTrafficType>84</CommercialTrafficType>
      <TrainActivity>
        <TrainActivityType>0001</TrainActivityType>
      </TrainActivity>
      <OperationalTrainNumber>3915</OperationalTrainNumber>
      <NetworkSpecificParameter>
        <Name>CZPassengerServiceNumber</Name>
        <Value>7204</Value>
      </NetworkSpecificParameter>
      <NetworkSpecificParameter>
        <Name>CZPublicService</Name>
        <Value>1</Value>
      </NetworkSpecificParameter>
      <NetworkSpecificParameter>
        <Name>CZPassengerPublicTransportOrderingCoName</Name>
        <Value>Zlínský kraj</Value>
      </NetworkSpecificParameter>
      <NetworkSpecificParameter>
        <Name>CZAlternativeTransport</Name>
        <Value>0</Value>
      </NetworkSpecificParameter>
      <NetworkSpecificParameter>
        <Name>CZPassengerDwellTime</Name>
        <Value>1</Value>
      </NetworkSpecificParameter>
    </CZPTTLocation>
    <CZPTTLocation>
      <Location>
        <CountryCodeISO>CZ</CountryCodeISO>
        <LocationPrimaryCode>34476</LocationPrimaryCode>
        <PrimaryLocationName>hr.VUSC 0710/0720 05</PrimaryLocationName>
      </Location>
      <TimingAtLocation>
        <Timing TimingQualifierCode="ALA">
          <Time>10:06:30.0000000+01:00</Time>
          <Offset>0</Offset>
        </Timing>
        <Timing TimingQualifierCode="ALD">
          <Time>10:06:30.0000000+01:00</Time>
          <Offset>0</Offset>
        </Timing>
      </TimingAtLocation>
      <ResponsibleRU>1154</ResponsibleRU>
      <ResponsibleIM>54</ResponsibleIM>
      <TrainType>1</TrainType>
      <TrafficType>11</TrafficType>
      <CommercialTrafficType>84</CommercialTrafficType>
      <OperationalTrainNumber>3915</OperationalTrainNumber>
      <NetworkSpecificParameter>
        <Name>CZPassengerServiceNumber</Name>
        <Value>7204</Value>
      </NetworkSpecificParameter>
      <NetworkSpecificParameter>
        <Name>CZPublicService</Name>
        <Value>1</Value>
      </NetworkSpecificParameter>
      <NetworkSpecificParameter>
        <Name>CZPassengerPublicTransportOrderingCoName</Name>
        <Value>Zlínský kraj</Value>
      </NetworkSpecificParameter>
      <NetworkSpecificParameter>
        <Name>CZAlternativeTransport</Name>
        <Value>0</Value>
      </NetworkSpecificParameter>
    </CZPTTLocation>
    <CZPTTLocation>
      <Location>
        <CountryCodeISO>CZ</CountryCodeISO>
        <LocationPrimaryCode>34485</LocationPrimaryCode>
        <PrimaryLocationName>Bezměrov</PrimaryLocationName>
      </Location>
      <TimingAtLocation>
        <Timing TimingQualifierCode="ALA">
          <Time>10:07:30.0000000+01:00</Time>
          <Offset>0</Offset>
        </Timing>
        <Timing TimingQualifierCode="ALD">
          <Time>10:07:30.0000000+01:00</Time>
          <Offset>0</Offset>
        </Timing>
      </TimingAtLocation>
      <ResponsibleRU>1154</ResponsibleRU>
      <ResponsibleIM>54</ResponsibleIM>
      <TrainType>1</TrainType>
      <TrafficType>11</TrafficType>
      <CommercialTrafficType>84</CommercialTrafficType>
      <TrainActivity>
        <TrainActivityType>0001</TrainActivityType>
      </TrainActivity>
      <TrainActivity>
        <TrainActivityType>CZ02</TrainActivityType>
      </TrainActivity>
      <TrainActivity>
        <TrainActivityType>0030</TrainActivityType>
      </TrainActivity>
      <OperationalTrainNumber>3915</OperationalTrainNumber>
      <NetworkSpecificParameter>
        <Name>CZPassengerServiceNumber</Name>
        <Value>7204</Value>
      </NetworkSpecificParameter>
      <NetworkSpecificParameter>
        <Name>CZPublicService</Name>
        <Value>1</Value>
      </NetworkSpecificParameter>
      <NetworkSpecificParameter>
        <Name>CZPassengerPublicTransportOrderingCoName</Name>
        <Value>Zlínský kraj</Value>
      </NetworkSpecificParameter>
      <NetworkSpecificParameter>
        <Name>CZAlternativeTransport</Name>
        <Value>0</Value>
      </NetworkSpecificParameter>
      <NetworkSpecificParameter>
        <Name>CZPassengerDwellTime</Name>
        <Value>1</Value>
      </NetworkSpecificParameter>
    </CZPTTLocation>
    <CZPTTLocation>
      <Location>
        <CountryCodeISO>CZ</CountryCodeISO>
        <LocationPrimaryCode>34515</LocationPrimaryCode>
        <PrimaryLocationName>Postoupky</PrimaryLocationName>
      </Location>
      <TimingAtLocation>
        <Timing TimingQualifierCode="ALA">
          <Time>10:10:30.0000000+01:00</Time>
          <Offset>0</Offset>
        </Timing>
        <Timing TimingQualifierCode="ALD">
          <Time>10:10:30.0000000+01:00</Time>
          <Offset>0</Offset>
        </Timing>
      </TimingAtLocation>
      <ResponsibleRU>1154</ResponsibleRU>
      <ResponsibleIM>54</ResponsibleIM>
      <TrainType>1</TrainType>
      <TrafficType>11</TrafficType>
      <CommercialTrafficType>84</CommercialTrafficType>
      <TrainActivity>
        <TrainActivityType>0001</TrainActivityType>
      </TrainActivity>
      <TrainActivity>
        <TrainActivityType>CZ02</TrainActivityType>
      </TrainActivity>
      <TrainActivity>
        <TrainActivityType>0030</TrainActivityType>
      </TrainActivity>
      <OperationalTrainNumber>3915</OperationalTrainNumber>
      <NetworkSpecificParameter>
        <Name>CZPassengerServiceNumber</Name>
        <Value>7204</Value>
      </NetworkSpecificParameter>
      <NetworkSpecificParameter>
        <Name>CZPublicService</Name>
        <Value>1</Value>
      </NetworkSpecificParameter>
      <NetworkSpecificParameter>
        <Name>CZPassengerPublicTransportOrderingCoName</Name>
        <Value>Zlínský kraj</Value>
      </NetworkSpecificParameter>
      <NetworkSpecificParameter>
        <Name>CZAlternativeTransport</Name>
        <Value>0</Value>
      </NetworkSpecificParameter>
      <NetworkSpecificParameter>
        <Name>CZPassengerDwellTime</Name>
        <Value>1</Value>
      </NetworkSpecificParameter>
    </CZPTTLocation>
    <CZPTTLocation>
      <Location>
        <CountryCodeISO>CZ</CountryCodeISO>
        <LocationPrimaryCode>34475</LocationPrimaryCode>
        <PrimaryLocationName>Kroměříž</PrimaryLocationName>
        <LocationSubsidiaryIdentification>
          <LocationSubsidiaryCode LocationSubsidiaryTypeCode="1">1a</LocationSubsidiaryCode>
          <AllocationCompany>0054</AllocationCompany>
        </LocationSubsidiaryIdentification>
      </Location>
      <TimingAtLocation>
        <Timing TimingQualifierCode="ALA">
          <Time>10:15:00.0000000+01:00</Time>
          <Offset>0</Offset>
        </Timing>
        <Timing TimingQualifierCode="ALD">
          <Time>10:17:00.0000000+01:00</Time>
          <Offset>0</Offset>
        </Timing>
        <DwellTime>2</DwellTime>
      </TimingAtLocation>
      <ResponsibleRU>1154</ResponsibleRU>
      <ResponsibleIM>54</ResponsibleIM>
      <TrainType>1</TrainType>
      <TrafficType>11</TrafficType>
      <CommercialTrafficType>84</CommercialTrafficType>
      <TrainActivity>
        <TrainActivityType>0001</TrainActivityType>
      </TrainActivity>
      <OperationalTrainNumber>3915</OperationalTrainNumber>
      <NetworkSpecificParameter>
        <Name>CZPassengerServiceNumber</Name>
        <Value>7204</Value>
      </NetworkSpecificParameter>
      <NetworkSpecificParameter>
        <Name>CZPublicService</Name>
        <Value>1</Value>
      </NetworkSpecificParameter>
      <NetworkSpecificParameter>
        <Name>CZPassengerPublicTransportOrderingCoName</Name>
        <Value>Zlínský kraj</Value>
      </NetworkSpecificParameter>
      <NetworkSpecificParameter>
        <Name>CZAlternativeTransport</Name>
        <Value>0</Value>
      </NetworkSpecificParameter>
      <NetworkSpecificParameter>
        <Name>CZPassengerDwellTime</Name>
        <Value>1</Value>
      </NetworkSpecificParameter>
    </CZPTTLocation>
    <CZPTTLocation>
      <Location>
        <CountryCodeISO>CZ</CountryCodeISO>
        <LocationPrimaryCode>33986</LocationPrimaryCode>
        <PrimaryLocationName>Km 15,500</PrimaryLocationName>
      </Location>
      <TimingAtLocation>
        <Timing TimingQualifierCode="ALA">
          <Time>10:23:00.0000000+01:00</Time>
          <Offset>0</Offset>
        </Timing>
        <Timing TimingQualifierCode="ALD">
          <Time>10:23:00.0000000+01:00</Time>
          <Offset>0</Offset>
        </Timing>
      </TimingAtLocation>
      <ResponsibleRU>1154</ResponsibleRU>
      <ResponsibleIM>54</ResponsibleIM>
      <TrainType>1</TrainType>
      <TrafficType>11</TrafficType>
      <CommercialTrafficType>84</CommercialTrafficType>
      <OperationalTrainNumber>3915</OperationalTrainNumber>
      <NetworkSpecificParameter>
        <Name>CZPassengerServiceNumber</Name>
        <Value>7204</Value>
      </NetworkSpecificParameter>
      <NetworkSpecificParameter>
        <Name>CZPublicService</Name>
        <Value>1</Value>
      </NetworkSpecificParameter>
      <NetworkSpecificParameter>
        <Name>CZPassengerPublicTransportOrderingCoName</Name>
        <Value>Zlínský kraj</Value>
      </NetworkSpecificParameter>
      <NetworkSpecificParameter>
        <Name>CZAlternativeTransport</Name>
        <Value>0</Value>
      </NetworkSpecificParameter>
    </CZPTTLocation>
    <CZPTTLocation>
      <Location>
        <CountryCodeISO>CZ</CountryCodeISO>
        <LocationPrimaryCode>33985</LocationPrimaryCode>
        <PrimaryLocationName>Hulín</PrimaryLocationName>
        <LocationSubsidiaryIdentification>
          <LocationSubsidiaryCode LocationSubsidiaryTypeCode="1">13a</LocationSubsidiaryCode>
          <AllocationCompany>0054</AllocationCompany>
        </LocationSubsidiaryIdentification>
      </Location>
      <TimingAtLocation>
        <Timing TimingQualifierCode="ALA">
          <Time>10:25:00.0000000+01:00</Time>
          <Offset>0</Offset>
        </Timing>
        <Timing TimingQualifierCode="ALD">
          <Time>10:34:00.0000000+01:00</Time>
          <Offset>0</Offset>
        </Timing>
        <DwellTime>9</DwellTime>
      </TimingAtLocation>
      <ResponsibleRU>1154</ResponsibleRU>
      <ResponsibleIM>54</ResponsibleIM>
      <TrainType>1</TrainType>
      <TrafficType>11</TrafficType>
      <CommercialTrafficType>84</CommercialTrafficType>
      <TrainActivity>
        <TrainActivityType>0001</TrainActivityType>
      </TrainActivity>
      <OperationalTrainNumber>3915</OperationalTrainNumber>
      <NetworkSpecificParameter>
        <Name>CZPassengerServiceNumber</Name>
        <Value>7204</Value>
      </NetworkSpecificParameter>
      <NetworkSpecificParameter>
        <Name>CZPublicService</Name>
        <Value>1</Value>
      </NetworkSpecificParameter>
      <NetworkSpecificParameter>
        <Name>CZPassengerPublicTransportOrderingCoName</Name>
        <Value>Zlínský kraj</Value>
      </NetworkSpecificParameter>
      <NetworkSpecificParameter>
        <Name>CZAlternativeTransport</Name>
        <Value>0</Value>
      </NetworkSpecificParameter>
      <NetworkSpecificParameter>
        <Name>CZPassengerDwellTime</Name>
        <Value>1</Value>
      </NetworkSpecificParameter>
    </CZPTTLocation>
    <CZPTTLocation>
      <Location>
        <CountryCodeISO>CZ</CountryCodeISO>
        <LocationPrimaryCode>34005</LocationPrimaryCode>
        <PrimaryLocationName>Třebětice</PrimaryLocationName>
        <LocationSubsidiaryIdentification>
          <LocationSubsidiaryCode LocationSubsidiaryTypeCode="1">1</LocationSubsidiaryCode>
          <AllocationCompany>0054</AllocationCompany>
        </LocationSubsidiaryIdentification>
      </Location>
      <TimingAtLocation>
        <Timing TimingQualifierCode="ALA">
          <Time>10:38:30.0000000+01:00</Time>
          <Offset>0</Offset>
        </Timing>
        <Timing TimingQualifierCode="ALD">
          <Time>10:39:00.0000000+01:00</Time>
          <Offset>0</Offset>
        </Timing>
        <DwellTime>0.5</DwellTime>
      </TimingAtLocation>
      <ResponsibleRU>1154</ResponsibleRU>
      <ResponsibleIM>54</ResponsibleIM>
      <TrainType>1</TrainType>
      <TrafficType>11</TrafficType>
      <CommercialTrafficType>84</CommercialTrafficType>
      <TrainActivity>
        <TrainActivityType>0001</TrainActivityType>
      </TrainActivity>
      <OperationalTrainNumber>3915</OperationalTrainNumber>
      <NetworkSpecificParameter>
        <Name>CZPassengerServiceNumber</Name>
        <Value>7204</Value>
      </NetworkSpecificParameter>
      <NetworkSpecificParameter>
        <Name>CZPublicService</Name>
        <Value>1</Value>
      </NetworkSpecificParameter>
      <NetworkSpecificParameter>
        <Name>CZPassengerPublicTransportOrderingCoName</Name>
        <Value>Zlínský kraj</Value>
      </NetworkSpecificParameter>
      <NetworkSpecificParameter>
        <Name>CZAlternativeTransport</Name>
        <Value>0</Value>
      </NetworkSpecificParameter>
      <NetworkSpecificParameter>
        <Name>CZPassengerDwellTime</Name>
        <Value>1</Value>
      </NetworkSpecificParameter>
    </CZPTTLocation>
    <CZPTTLocation>
      <Location>
        <CountryCodeISO>CZ</CountryCodeISO>
        <LocationPrimaryCode>38874</LocationPrimaryCode>
        <PrimaryLocationName>vl. v km 22,156</PrimaryLocationName>
      </Location>
      <TimingAtLocation>
        <Timing TimingQualifierCode="ALA">
          <Time>10:41:00.0000000+01:00</Time>
          <Offset>0</Offset>
        </Timing>
        <Timing TimingQualifierCode="ALD">
          <Time>10:41:00.0000000+01:00</Time>
          <Offset>0</Offset>
        </Timing>
      </TimingAtLocation>
      <ResponsibleRU>1154</ResponsibleRU>
      <ResponsibleIM>54</ResponsibleIM>
      <TrainType>1</TrainType>
      <TrafficType>11</TrafficType>
      <CommercialTrafficType>84</CommercialTrafficType>
      <OperationalTrainNumber>3915</OperationalTrainNumber>
      <NetworkSpecificParameter>
        <Name>CZPassengerServiceNumber</Name>
        <Value>7204</Value>
      </NetworkSpecificParameter>
      <NetworkSpecificParameter>
        <Name>CZPublicService</Name>
        <Value>1</Value>
      </NetworkSpecificParameter>
      <NetworkSpecificParameter>
        <Name>CZPassengerPublicTransportOrderingCoName</Name>
        <Value>Zlínský kraj</Value>
      </NetworkSpecificParameter>
      <NetworkSpecificParameter>
        <Name>CZAlternativeTransport</Name>
        <Value>0</Value>
      </NetworkSpecificParameter>
    </CZPTTLocation>
    <CZPTTLocation>
      <Location>
        <CountryCodeISO>CZ</CountryCodeISO>
        <LocationPrimaryCode>33855</LocationPrimaryCode>
        <PrimaryLocationName>Holešov</PrimaryLocationName>
        <LocationSubsidiaryIdentification>
          <LocationSubsidiaryCode LocationSubsidiaryTypeCode="1">1</LocationSubsidiaryCode>
          <AllocationCompany>0054</AllocationCompany>
        </LocationSubsidiaryIdentification>
      </Location>
      <TimingAtLocation>
        <Timing TimingQualifierCode="ALA">
          <Time>10:43:00.0000000+01:00</Time>
          <Offset>0</Offset>
        </Timing>
        <Timing TimingQualifierCode="ALD">
          <Time>10:44:00.0000000+01:00</Time>
          <Offset>0</Offset>
        </Timing>
        <DwellTime>1</DwellTime>
      </TimingAtLocation>
      <ResponsibleRU>1154</ResponsibleRU>
      <ResponsibleIM>54</ResponsibleIM>
      <TrainType>1</TrainType>
      <TrafficType>11</TrafficType>
      <CommercialTrafficType>84</CommercialTrafficType>
      <TrainActivity>
        <TrainActivityType>0001</TrainActivityType>
      </TrainActivity>
      <OperationalTrainNumber>3915</OperationalTrainNumber>
      <NetworkSpecificParameter>
        <Name>CZPassengerServiceNumber</Name>
        <Value>7204</Value>
      </NetworkSpecificParameter>
      <NetworkSpecificParameter>
        <Name>CZPublicService</Name>
        <Value>1</Value>
      </NetworkSpecificParameter>
      <NetworkSpecificParameter>
        <Name>CZPassengerPublicTransportOrderingCoName</Name>
        <Value>Zlínský kraj</Value>
      </NetworkSpecificParameter>
      <NetworkSpecificParameter>
        <Name>CZAlternativeTransport</Name>
        <Value>0</Value>
      </NetworkSpecificParameter>
      <NetworkSpecificParameter>
        <Name>CZPassengerDwellTime</Name>
        <Value>1</Value>
      </NetworkSpecificParameter>
    </CZPTTLocation>
    <CZPTTLocation>
      <Location>
        <CountryCodeISO>CZ</CountryCodeISO>
        <LocationPrimaryCode>33865</LocationPrimaryCode>
        <PrimaryLocationName>Dobrotice</PrimaryLocationName>
      </Location>
      <TimingAtLocation>
        <Timing TimingQualifierCode="ALA">
          <Time>10:48:00.0000000+01:00</Time>
          <Offset>0</Offset>
        </Timing>
        <Timing TimingQualifierCode="ALD">
          <Time>10:48:00.0000000+01:00</Time>
          <Offset>0</Offset>
        </Timing>
      </TimingAtLocation>
      <ResponsibleRU>1154</ResponsibleRU>
      <ResponsibleIM>54</ResponsibleIM>
      <TrainType>1</TrainType>
      <TrafficType>11</TrafficType>
      <CommercialTrafficType>84</CommercialTrafficType>
      <TrainActivity>
        <TrainActivityType>0001</TrainActivityType>
      </TrainActivity>
      <TrainActivity>
        <TrainActivityType>CZ02</TrainActivityType>
      </TrainActivity>
      <TrainActivity>
        <TrainActivityType>0030</TrainActivityType>
      </TrainActivity>
      <OperationalTrainNumber>3915</OperationalTrainNumber>
      <NetworkSpecificParameter>
        <Name>CZPassengerServiceNumber</Name>
        <Value>7204</Value>
      </NetworkSpecificParameter>
      <NetworkSpecificParameter>
        <Name>CZPublicService</Name>
        <Value>1</Value>
      </NetworkSpecificParameter>
      <NetworkSpecificParameter>
        <Name>CZPassengerPublicTransportOrderingCoName</Name>
        <Value>Zlínský kraj</Value>
      </NetworkSpecificParameter>
      <NetworkSpecificParameter>
        <Name>CZAlternativeTransport</Name>
        <Value>0</Value>
      </NetworkSpecificParameter>
      <NetworkSpecificParameter>
        <Name>CZPassengerDwellTime</Name>
        <Value>1</Value>
      </NetworkSpecificParameter>
    </CZPTTLocation>
    <CZPTTLocation>
      <Location>
        <CountryCodeISO>CZ</CountryCodeISO>
        <LocationPrimaryCode>33465</LocationPrimaryCode>
        <PrimaryLocationName>Jankovice</PrimaryLocationName>
      </Location>
      <TimingAtLocation>
        <Timing TimingQualifierCode="ALA">
          <Time>10:50:30.0000000+01:00</Time>
          <Offset>0</Offset>
        </Timing>
        <Timing TimingQualifierCode="ALD">
          <Time>10:50:30.0000000+01:00</Time>
          <Offset>0</Offset>
        </Timing>
      </TimingAtLocation>
      <ResponsibleRU>1154</ResponsibleRU>
      <ResponsibleIM>54</ResponsibleIM>
      <TrainType>1</TrainType>
      <TrafficType>11</TrafficType>
      <CommercialTrafficType>84</CommercialTrafficType>
      <TrainActivity>
        <TrainActivityType>0001</TrainActivityType>
      </TrainActivity>
      <TrainActivity>
        <TrainActivityType>CZ02</TrainActivityType>
      </TrainActivity>
      <TrainActivity>
        <TrainActivityType>0030</TrainActivityType>
      </TrainActivity>
      <OperationalTrainNumber>3915</OperationalTrainNumber>
      <NetworkSpecificParameter>
        <Name>CZPassengerServiceNumber</Name>
        <Value>7204</Value>
      </NetworkSpecificParameter>
      <NetworkSpecificParameter>
        <Name>CZPublicService</Name>
        <Value>1</Value>
      </NetworkSpecificParameter>
      <NetworkSpecificParameter>
        <Name>CZPassengerPublicTransportOrderingCoName</Name>
        <Value>Zlínský kraj</Value>
      </NetworkSpecificParameter>
      <NetworkSpecificParameter>
        <Name>CZAlternativeTransport</Name>
        <Value>0</Value>
      </NetworkSpecificParameter>
      <NetworkSpecificParameter>
        <Name>CZPassengerDwellTime</Name>
        <Value>1</Value>
      </NetworkSpecificParameter>
    </CZPTTLocation>
    <CZPTTLocation>
      <Location>
        <CountryCodeISO>CZ</CountryCodeISO>
        <LocationPrimaryCode>33595</LocationPrimaryCode>
        <PrimaryLocationName>Hlinsko pod Hostýnem</PrimaryLocationName>
        <LocationSubsidiaryIdentification>
          <LocationSubsidiaryCode LocationSubsidiaryTypeCode="1">1</LocationSubsidiaryCode>
          <AllocationCompany>0054</AllocationCompany>
        </LocationSubsidiaryIdentification>
      </Location>
      <TimingAtLocation>
        <Timing TimingQualifierCode="ALA">
          <Time>10:53:00.0000000+01:00</Time>
          <Offset>0</Offset>
        </Timing>
        <Timing TimingQualifierCode="ALD">
          <Time>10:53:00.0000000+01:00</Time>
          <Offset>0</Offset>
        </Timing>
      </TimingAtLocation>
      <ResponsibleRU>1154</ResponsibleRU>
      <ResponsibleIM>54</ResponsibleIM>
      <TrainType>1</TrainType>
      <TrafficType>11</TrafficType>
      <CommercialTrafficType>84</CommercialTrafficType>
      <TrainActivity>
        <TrainActivityType>0001</TrainActivityType>
      </TrainActivity>
      <TrainActivity>
        <TrainActivityType>CZ02</TrainActivityType>
      </TrainActivity>
      <TrainActivity>
        <TrainActivityType>0030</TrainActivityType>
      </TrainActivity>
      <OperationalTrainNumber>3915</OperationalTrainNumber>
      <NetworkSpecificParameter>
        <Name>CZPassengerServiceNumber</Name>
        <Value>7204</Value>
      </NetworkSpecificParameter>
      <NetworkSpecificParameter>
        <Name>CZPublicService</Name>
        <Value>1</Value>
      </NetworkSpecificParameter>
      <NetworkSpecificParameter>
        <Name>CZPassengerPublicTransportOrderingCoName</Name>
        <Value>Zlínský kraj</Value>
      </NetworkSpecificParameter>
      <NetworkSpecificParameter>
        <Name>CZAlternativeTransport</Name>
        <Value>0</Value>
      </NetworkSpecificParameter>
      <NetworkSpecificParameter>
        <Name>CZPassengerDwellTime</Name>
        <Value>1</Value>
      </NetworkSpecificParameter>
    </CZPTTLocation>
    <CZPTTLocation>
      <Location>
        <CountryCodeISO>CZ</CountryCodeISO>
        <LocationPrimaryCode>33585</LocationPrimaryCode>
        <PrimaryLocationName>Bystřice pod Hostýnem</PrimaryLocationName>
        <LocationSubsidiaryIdentification>
          <LocationSubsidiaryCode LocationSubsidiaryTypeCode="1">1</LocationSubsidiaryCode>
          <AllocationCompany>0054</AllocationCompany>
        </LocationSubsidiaryIdentification>
      </Location>
      <TimingAtLocation>
        <Timing TimingQualifierCode="ALA">
          <Time>10:57:00.0000000+01:00</Time>
          <Offset>0</Offset>
        </Timing>
      </TimingAtLocation>
      <ResponsibleRU>1154</ResponsibleRU>
      <ResponsibleIM>54</ResponsibleIM>
      <TrainType>1</TrainType>
      <TrafficType>11</TrafficType>
      <CommercialTrafficType>84</CommercialTrafficType>
      <TrainActivity>
        <TrainActivityType>0001</TrainActivityType>
      </TrainActivity>
      <OperationalTrainNumber>3915</OperationalTrainNumber>
      <NetworkSpecificParameter>
        <Name>CZPassengerServiceNumber</Name>
        <Value>7204</Value>
      </NetworkSpecificParameter>
      <NetworkSpecificParameter>
        <Name>CZPublicService</Name>
        <Value>1</Value>
      </NetworkSpecificParameter>
      <NetworkSpecificParameter>
        <Name>CZPassengerPublicTransportOrderingCoName</Name>
        <Value>Zlínský kraj</Value>
      </NetworkSpecificParameter>
      <NetworkSpecificParameter>
        <Name>CZAlternativeTransport</Name>
        <Value>0</Value>
      </NetworkSpecificParameter>
      <NetworkSpecificParameter>
        <Name>CZPassengerDwellTime</Name>
        <Value>1</Value>
      </NetworkSpecificParameter>
    </CZPTTLocation>
    <PlannedCalendar>
      <BitmapDays>1000001100111110001011000001100000110000011000001100000110000011000001100000110000011000001100000110000011000011110000110000011000001100001110000111000001100000110000011000001100000110000011000001100000111000011000001100000110000011000001100000110000011000001100000110000011000001100000111000011000001100000110000011001001100000110000011010001100000110000011000001</BitmapDays>
      <ValidityPeriod>
        <StartDateTime>2025-12-14T00:00:00</StartDateTime>
        <EndDateTime>2026-12-12T00:00:00</EndDateTime>
      </ValidityPeriod>
    </PlannedCalendar>
  </CZPTTInformation>
  <NetworkSpecificParameter>
    <Name>CZIPTS</Name>
    <Value>74|CZ34306||CZ33585||</Value>
  </NetworkSpecificParameter>
  <NetworkSpecificParameter>
    <Name>CZCentralPTTNote</Name>
    <Value>17|CZ34306||CZ33585||0|</Value>
  </NetworkSpecificParameter>
  <NetworkSpecificParameter>
    <Name>CZCentralPTTNote</Name>
    <Value>22|CZ34306||CZ33585||0|</Value>
  </NetworkSpecificParameter>
  <NetworkSpecificParameter>
    <Name>CZCentralPTTNote</Name>
    <Value>40|CZ34306||CZ33585||0|</Value>
  </NetworkSpecificParameter>
  <NetworkSpecificParameter>
    <Name>CZCentralPTTNote</Name>
    <Value>30|CZ34306||CZ33585||0|</Value>
  </NetworkSpecificParameter>
</CZPTTCISMessage>